eoir/__init__.py
eoir/__version__.py
eoir/main.py
eoir/settings.py
eoir/cli/__init__.py
eoir/cli/clean.py
eoir/cli/config.py
eoir/cli/db.py
eoir/cli/download.py
eoir/cli/pipeline.py
eoir/core/__init__.py
eoir/core/clean.py
eoir/core/config.py
eoir/core/csv.py
eoir/core/db.py
eoir/core/db_utils.py
eoir/core/download.py
eoir/core/models.py
eoir/core/parallel.py
eoir/logging/__init__.py
eoir/logging/handlers.py
eoir/metadata/__init__.py
eoir/metadata/foia_tables.sql
eoir/metadata/post_copy.sql
eoir/metadata/tx.py
eoir/metadata/json/column-definitions.json
eoir/metadata/json/decode.json
eoir/metadata/json/lookups.json
eoir/metadata/json/tables.json
eoir/metadata/json/lookups/column-definitions.json
eoir/metadata/json/lookups/tblAdjournmentCodes.json
eoir/metadata/json/lookups/tblAdjournmentcode.json
eoir/metadata/json/lookups/tblAppealCategory.json
eoir/metadata/json/lookups/tblAttyLevel.json
eoir/metadata/json/lookups/tblAttyType.json
eoir/metadata/json/lookups/tblBarCodeType.json
eoir/metadata/json/lookups/tblDecCode.json
eoir/metadata/json/lookups/tblINSoffice.json
eoir/metadata/json/lookups/tblInmateHousing.json
eoir/metadata/json/lookups/tblLanguage.json
eoir/metadata/json/lookups/tblLookUpAllegationStmt.json
eoir/metadata/json/lookups/tblLookUpCaseIdentifier.json
eoir/metadata/json/lookups/tblLookUpDDDecisionType.json
eoir/metadata/json/lookups/tblLookUpINSAddre.json
eoir/metadata/json/lookups/tblLookUp_Appln.json
eoir/metadata/json/lookups/tblLookup3MbrReferredReason.json
eoir/metadata/json/lookups/tblLookupAlienNat.json
eoir/metadata/json/lookups/tblLookupAppealIssue.json
eoir/metadata/json/lookups/tblLookupBIA.json
eoir/metadata/json/lookups/tblLookupBIADecision.json
eoir/metadata/json/lookups/tblLookupBIADecisionType.json
eoir/metadata/json/lookups/tblLookupBaseCity.json
eoir/metadata/json/lookups/tblLookupBoardMotion.json
eoir/metadata/json/lookups/tblLookupCallup_Reason.json
eoir/metadata/json/lookups/tblLookupCaseType.json
eoir-0.0.1.dist-info/licenses/LICENSE
eoir-0.0.1.dist-info/METADATA
eoir-0.0.1.dist-info/WHEEL
eoir-0.0.1.dist-info/entry_points.txt
eoir-0.0.1.dist-info/top_level.txt
eoir-0.0.1.dist-info/RECORD
