Metadata-Version: 2.4
Name: eoir
Version: 0.0.1
Summary: EOIR FOIA data processing tools
Author-email: Backlog Immigration LLC <info@bklg.org>
Maintainer-email: Backlog Immigration LLC <info@bklg.org>
License-Expression: MIT
Project-URL: Homepage, https://github.com/marrowb/eoir
Project-URL: Repository, https://github.com/marrowb/eoir
Project-URL: Issues, https://github.com/marrowb/eoir/issues
Project-URL: Documentation, https://github.com/marrowb/eoir#readme
Keywords: eoir,foia,immigration,data-processing,etl
Classifier: Development Status :: 3 - Alpha
Classifier: Intended Audience :: Developers
Classifier: Intended Audience :: Legal Industry
Classifier: Programming Language :: Python :: 3
Classifier: Programming Language :: Python :: 3.10
Classifier: Topic :: Software Development :: Libraries :: Python Modules
Classifier: Topic :: Database
Requires-Python: >=3.10
License-File: LICENSE
Requires-Dist: click>=8.1.8
Requires-Dist: psycopg==3.2.1
Requires-Dist: python-dotenv>=1.0.1
Requires-Dist: requests>=2.32.3
Requires-Dist: structlog>=24.1.0
Requires-Dist: zipfile-deflate64>=0.2.0
Dynamic: license-file
